indeedjobsearch/indeedjobsearch.py
indeedjobsearch/test.py
indeedjobsearch-6.2.0.dist-info/LICENSE
indeedjobsearch-6.2.0.dist-info/METADATA
indeedjobsearch-6.2.0.dist-info/WHEEL
indeedjobsearch-6.2.0.dist-info/top_level.txt
indeedjobsearch-6.2.0.dist-info/RECORD
