Metadata-Version: 2.1
Name: indeedjobsearch
Version: 6.2.0
Summary: 
Home-page: https://github.com/soumilshah1995/Indeed-Job-Search-Bot/blob/master/README.md
Author: Soumil Nitin Shah
Author-email: soushah@my.bridgeport.edu
License: MIT
Platform: UNKNOWN
Classifier: License :: OSI Approved :: MIT License
Classifier: Programming Language :: Python :: 3
Classifier: Programming Language :: Python :: 3.7
Requires-Dist: pandas
Requires-Dist: bs4
Requires-Dist: requests
